voronoids-0.1.0.dist-info/METADATA
voronoids-0.1.0.dist-info/WHEEL
voronoids/__init__.py
voronoids/voronoids.cpython-310-x86_64-linux-gnu.so
voronoids-0.1.0.dist-info/RECORD
