Metadata-Version: 2.3
Name: voronoids
Version: 0.1.0
Summary: A library for generating Voronoi diagrams in parallel in Rust.
Author: Kaze Wong <kazewong.physics@gmail.com>
Author-email: Kaze Wong <kazewong.physics@gmail.com>
License: MIT
